contributor_3/__init__.py
contributor_3/app.py
contributor_3/app_query_engine.py
contributor_3-0.2.1.dist-info/METADATA
contributor_3-0.2.1.dist-info/WHEEL
contributor_3-0.2.1.dist-info/RECORD
